LICENSE
tworg/__init__.py
tworg/__main__.py
tworg/console.py
tworg/tworg.py
tworg-0.1.0.dist-info/entry_points.txt
tworg-0.1.0.dist-info/LICENSE
tworg-0.1.0.dist-info/WHEEL
tworg-0.1.0.dist-info/METADATA
tworg-0.1.0.dist-info/RECORD
