Metadata-Version: 2.1
Name: tworg
Version: 0.1.0
Summary: Convert TiddlyWiki tiddler files to Org Mode
Home-page: https://github.com/kylerjohnston/tworg
License: MIT
Author: Kyle Johnston
Author-email: kyle@muumu.us
Requires-Python: >=3.9,<4.0
Classifier: License :: OSI Approved :: MIT License
Classifier: Programming Language :: Python :: 3
Project-URL: Repository, https://github.com/kylerjohnston/tworg
